madness_deblender/FlowVAEnet.py
madness_deblender/__init__.py
madness_deblender/callbacks.py
madness_deblender/deblender.py
madness_deblender/extraction.py
madness_deblender/losses.py
madness_deblender/model.py
madness_deblender/tests/test_deblender.py
madness_deblender/tests/test_extraction.py
madness_deblender/tests/test_training.py
madness_deblender/utils.py
madness_deblender-1.0.0.dist-info/LICENSE
madness_deblender-1.0.0.dist-info/METADATA
madness_deblender-1.0.0.dist-info/WHEEL
madness_deblender-1.0.0.dist-info/RECORD
