Metadata-Version: 2.3
Name: madness-deblender
Version: 1.0.0
Summary: Galaxy deblender from variational autoencoders
License: MIT
Keywords: galaxies,deblending,cosmology,generative models
Author: Biswajit Biswas
Author-email: biswas@apc.in2p3.fr
Requires-Python: >=3.9,<3.10
Classifier: License :: OSI Approved :: MIT License
Classifier: Programming Language :: Python :: 3
Classifier: Programming Language :: Python :: 3.9
Provides-Extra: dev
Provides-Extra: notebooks
Requires-Dist: astropy
Requires-Dist: galcheat
Requires-Dist: ipykernel ; extra == "notebooks" or extra == "dev"
Requires-Dist: jupyter ; extra == "notebooks" or extra == "dev"
Requires-Dist: matplotlib ; extra == "notebooks" or extra == "dev"
Requires-Dist: numpy
Requires-Dist: pandas
Requires-Dist: pre-commit ; extra == "dev"
Requires-Dist: pytest ; extra == "dev"
Requires-Dist: scikit-image
Requires-Dist: seaborn ; extra == "notebooks" or extra == "dev"
Requires-Dist: sep
Requires-Dist: tensorflow (==2.15) ; sys_platform == "linux"
Requires-Dist: tensorflow-macos (==2.15) ; sys_platform == "darwin"
Requires-Dist: tensorflow-probability (==0.23)
Project-URL: Repository, https://github.com/b-biswas/madness
